llms/__init__.py
llms/gemini.py
llms/gpt.py
llms/logger.py
groxai_llms-0.0.4.dist-info/LICENSE
groxai_llms-0.0.4.dist-info/METADATA
groxai_llms-0.0.4.dist-info/WHEEL
groxai_llms-0.0.4.dist-info/top_level.txt
groxai_llms-0.0.4.dist-info/RECORD
