Metadata-Version: 2.1
Name: groxai_llms
Version: 0.0.4
Summary: Helps to use the groxai_llms package for the devlopment
Home-page: https://github.com/Intrepid-AI/groxai_llms
Author: Intrepid-AI
Author-email: jaiyesh0002@gmail.com
Project-URL: Bug Tracker, https://github.com/Intrepid-AI/groxai_llms/issues
Requires-Python: >3.9
License-File: LICENSE
Requires-Dist: openai ==1.37.0
Requires-Dist: google-generativeai ==0.7.2
Provides-Extra: testing
Requires-Dist: pytest ; extra == 'testing'
Requires-Dist: mypy ; extra == 'testing'
Requires-Dist: flake8 ; extra == 'testing'
Requires-Dist: tox ; extra == 'testing'
Requires-Dist: black ; extra == 'testing'
